MidBrain/MidBrain.py
MidBrain/__init__.py
MidBrain-1.2.3.dist-info/LICENSE
MidBrain-1.2.3.dist-info/METADATA
MidBrain-1.2.3.dist-info/WHEEL
MidBrain-1.2.3.dist-info/entry_points.txt
MidBrain-1.2.3.dist-info/top_level.txt
MidBrain-1.2.3.dist-info/RECORD
