Metadata-Version: 2.1
Name: MidBrain
Version: 1.2.3
Summary: Your magical CLI for generating text spells and performing tasks.
Home-page: https://github.com/harshitkulkarni22/hokus-pokus
Author: Harshit Kulkarni
Author-email: harshitkulkarni22@gmail.com
Classifier: Programming Language :: Python :: 3
Classifier: License :: OSI Approved :: MIT License
Classifier: Operating System :: OS Independent
License-File: LICENSE
Requires-Dist: openai
Requires-Dist: colorama (>=0.4.6)
Requires-Dist: transformers (>=4.0.0)
Requires-Dist: torch (>=1.8.0)
Requires-Dist: click
